epc/__init__.py
epc/_version.py
epc/data/lense_calibration_narrow_field.csv
epc/data/lense_calibration_standard_field.csv
epc/data/lense_calibration_wide_field.csv
epc/tofCam611/__init__.py
epc/tofCam611/camera.py
epc/tofCam611/commandList.py
epc/tofCam611/communicationType.py
epc/tofCam611/serialInterface.py
epc/tofCam611/tofCam611.py
epc/tofCam611/update.py
epc/tofCam611/constants/__calibration.py
epc/tofCam611/constants/__constants.py
epc/tofCam611/constants/__epc611.py
epc/tofCam611/constants/__epc611SpiRegister.py
epc/tofCam611/constants/__epc611SpiRegisterSettings.py
epc/tofCam611/constants/__init__.py
epc/tofCam611/constants/__modFrequency.py
epc/tofCam611/constants/__mode.py
epc/tofCam611/constants/__writeCalibrationData.py
epc/tofCam635/__init__.py
epc/tofCam635/commands.py
epc/tofCam635/tofCam635.py
epc/tofCam635/tofcam635Header.py
epc/tofCam635/communication/__init__.py
epc/tofCam635/communication/serialInterface.py
epc/tofCam635/communication/communicationConstants/__init__.py
epc/tofCam635/communication/communicationConstants/command.py
epc/tofCam635/communication/communicationConstants/commandList.py
epc/tofCam635/communication/communicationConstants/data.py
epc/tofCam635/communication/communicationConstants/identification.py
epc/tofCam635/communication/communicationConstants/type.py
epc/tofCam635/communication/communicationConstants/update.py
epc/tofCam635/constants/__constants.py
epc/tofCam635/constants/__init__.py
epc/tofCam635/constants/__modFrequency.py
epc/tofCam635/constants/__mode.py
epc/tofCam635/constants/__writeCalibrationData.py
epc/tofCam660/__init__.py
epc/tofCam660/command.py
epc/tofCam660/crc.py
epc/tofCam660/epc660.py
epc/tofCam660/interface.py
epc/tofCam660/mac_address_generator.py
epc/tofCam660/memory.py
epc/tofCam660/parser.py
epc/tofCam660/productfactory.py
epc/tofCam660/response.py
epc/tofCam660/server.py
epc/tofCam660/tofCam660.py
epc/tofCam660/trace_interface.py
epc/tofCam660/usb_interface.py
epc/tofCam_gui/__init__.py
epc_tofcam_toolkit-0.1.1.dist-info/LICENSE.txt
epc_tofcam_toolkit-0.1.1.dist-info/METADATA
epc_tofcam_toolkit-0.1.1.dist-info/WHEEL
epc_tofcam_toolkit-0.1.1.dist-info/entry_points.txt
epc_tofcam_toolkit-0.1.1.dist-info/top_level.txt
epc_tofcam_toolkit-0.1.1.dist-info/RECORD
