Metadata-Version: 2.2
Name: epc-tofcam-toolkit
Version: 0.1.1
Summary: "Toolkit for ESPROS TOFcam's"
Home-page: https://www.espros.com
Author: "EPC"
Author-email: "info@espros.com"
Project-URL: Documentation, https://epc-tofcam-toolkit.readthedocs.io/en/latest/
Project-URL: Source, https://github.com/espros/epc-tofcam-toolkit
Keywords: TOF,TOFcam,ESPROS,EPC,Toolkit,pointcloud,3D,time of flight,TOF camera
License-File: LICENSE.txt
Requires-Dist: numpy>=2.0.0
Requires-Dist: matplotlib>=3.10.0
Requires-Dist: pillow>=11.0.0
Requires-Dist: opencv-python>=4.10.0.84
Requires-Dist: pyqtgraph>=0.13.7
Requires-Dist: PySide6>=6.8.1
Requires-Dist: pyserial>=3.5
Requires-Dist: scipy>=1.14.1
Requires-Dist: PyQtDarkTheme-fork==2.3.2
Requires-Dist: qtconsole>=5.6.1
Requires-Dist: ipython>=8.30.0
Requires-Dist: pyopengl>=3.1.7
